spacytextblob/__init__.py
spacytextblob/spacytextblob.py
spacytextblob-0.1.6.dist-info/LICENSE
spacytextblob-0.1.6.dist-info/WHEEL
spacytextblob-0.1.6.dist-info/METADATA
spacytextblob-0.1.6.dist-info/RECORD
