Metadata-Version: 2.1
Name: spacytextblob
Version: 0.1.6
Summary: A TextBlob sentiment analysis pipeline compponent for spaCy
Home-page: https://github.com/SamEdwardes/spaCyTextBlob
License: MIT
Keywords: python,spacy,textblob,nlp
Author: SamEdwardes
Author-email: edwardes.s@gmail.com
Requires-Python: >=3.6.9,<4.0.0
Classifier: License :: OSI Approved :: MIT License
Classifier: Programming Language :: Python :: 3
Classifier: Programming Language :: Python :: 3.7
Classifier: Programming Language :: Python :: 3.8
Classifier: Programming Language :: Python :: 3.9
Requires-Dist: spacy (>=2.3.2,<3.0.0)
Requires-Dist: textblob (>=0.15.3,<0.16.0)
Project-URL: Documentation, https://spacytextblob.netlify.app/
Project-URL: Repository, https://github.com/SamEdwardes/spaCyTextBlob
